cl/__init__.py
cl/closed_loop.py
cl/data_stream.py
cl/neurons.py
cl/recording.py
cl/stim_plan.py
cl/util/__init__.py
cl/util/plot.py
cl/util/recording_view.py
cl/util/util.py
cl_sdk-0.1.0.dist-info/METADATA
cl_sdk-0.1.0.dist-info/WHEEL
cl_sdk-0.1.0.dist-info/licenses/LICENSE
cl_sdk-0.1.0.dist-info/RECORD
