Metadata-Version: 2.4
Name: cl-sdk
Version: 0.1.0
Summary: Simulator for the Cortical Labs cl API
Project-URL: Homepage, https://github.com/Cortical-Labs/cl-sdk
Project-URL: Documentation, https://github.com/Cortical-Labs/cl-sdk
Project-URL: Source, https://github.com/Cortical-Labs/cl-sdk
Author-email: Cortical Labs Pte Ltd <info@corticallabs.com>
License: CC BY-NC 4.0
License-File: LICENSE
Classifier: License :: Other/Proprietary License
Classifier: Operating System :: OS Independent
Classifier: Programming Language :: Python :: 3
Requires-Python: >=3.10.0
Requires-Dist: dotenv
Requires-Dist: matplotlib
Requires-Dist: msgpack
Requires-Dist: msgpack-numpy
Requires-Dist: numpy
Requires-Dist: tables
Provides-Extra: test
Requires-Dist: inline-snapshot[black]; extra == 'test'
Requires-Dist: matplotlib; extra == 'test'
Requires-Dist: pytest; extra == 'test'
Requires-Dist: pytest-mock; extra == 'test'
